setup.py
dsnd_probs/Binomialdistribution.py
dsnd_probs/Gaussiandistribution.py
dsnd_probs/Generaldistribution.py
dsnd_probs/__init__.py
dsnd_probs.egg-info/PKG-INFO
dsnd_probs.egg-info/SOURCES.txt
dsnd_probs.egg-info/dependency_links.txt
dsnd_probs.egg-info/not-zip-safe
dsnd_probs.egg-info/top_level.txt