Metadata-Version: 1.0
Name: dsnd-probs
Version: 0.1
Summary: Gaussian distributions
Home-page: UNKNOWN
Author: Soro Kolotioloma
Author-email: ksoro17@alustudent.com
License: UNKNOWN
Platform: UNKNOWN
